pyDataViz/__init__.py
pyDataViz/hist.py
pyDataViz-0.0.9.dist-info/LICENSE
pyDataViz-0.0.9.dist-info/METADATA
pyDataViz-0.0.9.dist-info/WHEEL
pyDataViz-0.0.9.dist-info/top_level.txt
pyDataViz-0.0.9.dist-info/RECORD
