Metadata-Version: 2.1
Name: pyDataViz
Version: 0.0.9
Summary: A package for data visualization created by Amir H
Author-email: Amir H <amirh.hassanpour@gmail.com>
License: Copyright (c) 2018 The Python Packaging Authority        
Project-URL: Homepage, https://github.com/amirhhassanpour/pyDataViz
Project-URL: Bug Tracker, https://github.com/amirhhassanpour/pyDataViz/issues
Classifier: Programming Language :: Python :: 3
Classifier: License :: OSI Approved :: MIT License
Classifier: Operating System :: OS Independent
Requires-Python: >=3.7
License-File: LICENSE
